README.md
setup.py
setup_py/__init__.py
setup_py/cli.py
setup_py/generator.py
setup_py_cli.egg-info/PKG-INFO
setup_py_cli.egg-info/SOURCES.txt
setup_py_cli.egg-info/dependency_links.txt
setup_py_cli.egg-info/entry_points.txt
setup_py_cli.egg-info/not-zip-safe
setup_py_cli.egg-info/top_level.txt