Metadata-Version: 2.1
Name: setup-py-cli
Version: 2.0.1
Summary: Simple module to generate setup.py template.
Home-page: https://github.com/VoIlAlex/setup-py
Author: Ilya Vouk
Author-email: ilya.vouk@gmail.com
License: MIT
Download-URL: https://github.com/VoIlAlex/setup-py/archive/v2.0.1.tar.gz
Keywords: generator,setup,distribution,devtools
Platform: UNKNOWN
Classifier: Development Status :: 3 - Alpha
Classifier: Topic :: Software Development :: Code Generators
Classifier: Topic :: Software Development :: Libraries
Classifier: Topic :: Utilities
Classifier: Topic :: System :: Installation/Setup
Classifier: Intended Audience :: Developers
Classifier: License :: OSI Approved :: MIT License
Classifier: Programming Language :: Python :: 3
Classifier: Programming Language :: Python :: 3.4
Classifier: Programming Language :: Python :: 3.5
Classifier: Programming Language :: Python :: 3.6
Classifier: Programming Language :: Python :: 3.7
